LICENSE
README.md
setup.py
InputDriverFTC/FieldDisplay.py
InputDriverFTC/FieldDisplayRobot.py
InputDriverFTC/__init__.py
InputDriverFTC/main.py
InputDriverFTC.egg-info/PKG-INFO
InputDriverFTC.egg-info/SOURCES.txt
InputDriverFTC.egg-info/dependency_links.txt
InputDriverFTC.egg-info/requires.txt
InputDriverFTC.egg-info/top_level.txt