Metadata-Version: 2.1
Name: InputDriverFTC
Version: 0.2
Summary: Pathing library for FTC robotics.
Author: Tiernan Lindauer
Author-email: <tiernanxkl@gmail.com>
Keywords: python,FTC,autonomous,robotics
Classifier: Intended Audience :: Developers
Classifier: Programming Language :: Python :: 3
Classifier: Operating System :: Unix
Classifier: Operating System :: MacOS :: MacOS X
Classifier: Operating System :: Microsoft :: Windows
License-File: LICENSE
